[{"tripId":"14955233","time":"09:25:03"},{"tripId":"14955235","time":"07:54:21"},{"tripId":"14955234","time":"08:23:21"},{"tripId":"14955237","time":"06:54:54"},{"tripId":"14955236","time":"07:23:29"},{"tripId":"14955239","time":"05:59:54"},{"tripId":"14955238","time":"06:22:54"},{"tripId":"15254001","time":"10:55:12"},{"tripId":"15254000","time":"10:25:12"},{"tripId":"15254003","time":"11:55:12"},{"tripId":"15254002","time":"11:25:12"},{"tripId":"15254005","time":"12:55:12"},{"tripId":"15254004","time":"12:25:12"},{"tripId":"15254007","time":"13:55:12"},{"tripId":"15254006","time":"13:25:12"},{"tripId":"15254009","time":"14:57:12"},{"tripId":"15254008","time":"14:24:12"},{"tripId":"15253985","time":"07:54:21"},{"tripId":"15253984","time":"08:23:21"},{"tripId":"15253987","time":"06:54:54"},{"tripId":"15253983","time":"09:25:03"},{"tripId":"15253989","time":"05:59:54"},{"tripId":"15253988","time":"06:22:54"},{"tripId":"15254014","time":"21:33:21"},{"tripId":"15254012","time":"20:33:21"},{"tripId":"15254013","time":"21:03:21"},{"tripId":"15254010","time":"19:32:21"},{"tripId":"15073663","time":"20:33:21"},{"tripId":"15253992","time":"18:02:30"},{"tripId":"15253993","time":"17:34:14"},{"tripId":"15253990","time":"19:03:21"},{"tripId":"15253991","time":"18:28:55"},{"tripId":"15253996","time":"15:28:03"},{"tripId":"15253997","time":"09:56:03"},{"tripId":"15253994","time":"17:04:14"},{"tripId":"15253995","time":"16:02:21"},{"tripId":"15253998","time":"16:32:21"},{"tripId":"15253999","time":"08:52:21"},{"tripId":"14955257","time":"13:55:12"},{"tripId":"14955256","time":"13:25:12"},{"tripId":"14955255","time":"12:55:12"},{"tripId":"14955254","time":"12:25:12"},{"tripId":"14955253","time":"11:55:12"},{"tripId":"14955252","time":"11:25:12"},{"tripId":"14955251","time":"10:55:12"},{"tripId":"14955250","time":"10:25:12"},{"tripId":"14955259","time":"14:57:12"},{"tripId":"14955258","time":"14:24:12"},{"tripId":"15073664","time":"21:03:21"},{"tripId":"15073665","time":"21:33:21"},{"tripId":"15073662","time":"20:03:21"},{"tripId":"15073661","time":"19:32:21"},{"tripId":"14955244","time":"17:05:21"},{"tripId":"14955245","time":"16:02:21"},{"tripId":"14955246","time":"15:29:47"},{"tripId":"14955247","time":"09:56:03"},{"tripId":"14955240","time":"19:03:21"},{"tripId":"14955241","time":"18:28:55"},{"tripId":"14955242","time":"18:03:03"},{"tripId":"14955243","time":"17:34:47"},{"tripId":"14955248","time":"16:32:21"},{"tripId":"14955249","time":"08:52:21"},{"tripId":"15253986","time":"07:23:29"},{"tripId":"15254011","time":"20:03:21"}]