[{"tripId":"15259112","time":"17:47:38"},{"tripId":"14960349","time":"17:49:38"},{"tripId":"14960348","time":"18:55:42"},{"tripId":"14960347","time":"17:33:23"},{"tripId":"15259110","time":"17:31:32"},{"tripId":"14960352","time":"18:31:42"},{"tripId":"14960353","time":"18:09:38"},{"tripId":"14960351","time":"16:52:23"},{"tripId":"14960354","time":"17:13:23"},{"tripId":"14960355","time":"16:29:38"},{"tripId":"15259129","time":"06:05:42"},{"tripId":"15259121","time":"17:14:23"},{"tripId":"15259125","time":"05:45:42"},{"tripId":"15259124","time":"06:44:51"},{"tripId":"15259127","time":"06:24:51"},{"tripId":"15259126","time":"07:04:51"},{"tripId":"14960362","time":"05:44:42"},{"tripId":"15259128","time":"05:25:42"},{"tripId":"14960367","time":"07:40:00"},{"tripId":"14960366","time":"06:06:42"},{"tripId":"14960365","time":"05:26:35"},{"tripId":"14960364","time":"06:26:51"},{"tripId":"14960361","time":"06:46:00"},{"tripId":"15259130","time":"07:40:51"},{"tripId":"15259111","time":"18:57:38"},{"tripId":"15259114","time":"16:53:23"},{"tripId":"15259115","time":"18:32:38"},{"tripId":"15259116","time":"18:10:38"},{"tripId":"15259117","time":"17:14:23"},{"tripId":"14960363","time":"07:06:00"},{"tripId":"15259122","time":"16:31:32"},{"tripId":"15259118","time":"16:31:32"}]