[{"tripId":"15261090","time":"13:48:00"},{"tripId":"15261091","time":"11:48:00"},{"tripId":"14961999","time":"05:33:54"},{"tripId":"15260774","time":"19:36:00"},{"tripId":"15260770","time":"17:09:09"},{"tripId":"15260771","time":"17:43:09"},{"tripId":"15260772","time":"18:22:00"},{"tripId":"15260773","time":"19:08:00"},{"tripId":"15261045","time":"19:48:06"},{"tripId":"15261092","time":"10:48:00"},{"tripId":"15261093","time":"09:48:00"},{"tripId":"15261070","time":"13:49:00"},{"tripId":"14962004","time":"08:17:17"},{"tripId":"14962005","time":"08:47:17"},{"tripId":"14962006","time":"16:41:17"},{"tripId":"14962007","time":"17:09:09"},{"tripId":"14962000","time":"06:08:09"},{"tripId":"14962001","time":"06:58:09"},{"tripId":"14962002","time":"07:28:09"},{"tripId":"14962003","time":"07:58:00"},{"tripId":"14962008","time":"17:43:09"},{"tripId":"14962009","time":"18:22:00"},{"tripId":"14962325","time":"15:48:00"},{"tripId":"14962324","time":"12:48:00"},{"tripId":"14962327","time":"13:48:00"},{"tripId":"14962326","time":"14:48:00"},{"tripId":"14962321","time":"19:43:00"},{"tripId":"14962320","time":"17:48:00"},{"tripId":"14962323","time":"18:43:00"},{"tripId":"14962322","time":"16:48:14"},{"tripId":"14962329","time":"10:48:00"},{"tripId":"14962328","time":"11:48:00"},{"tripId":"15261044","time":"20:48:06"},{"tripId":"15260763","time":"06:06:09"},{"tripId":"15260762","time":"05:31:38"},{"tripId":"15260769","time":"16:41:09"},{"tripId":"14962330","time":"09:48:00"},{"tripId":"15261037","time":"16:49:06"},{"tripId":"14962270","time":"13:50:14"},{"tripId":"15260767","time":"08:15:00"},{"tripId":"15260766","time":"07:56:17"},{"tripId":"15260765","time":"07:26:09"},{"tripId":"15260764","time":"06:56:09"},{"tripId":"15261041","time":"09:48:00"},{"tripId":"15261040","time":"10:52:00"},{"tripId":"15261043","time":"21:52:52"},{"tripId":"15261042","time":"14:50:00"},{"tripId":"14962307","time":"13:49:00"},{"tripId":"14962306","time":"14:49:14"},{"tripId":"14962303","time":"17:49:06"},{"tripId":"14962302","time":"18:51:06"},{"tripId":"14962301","time":"19:51:06"},{"tripId":"14962300","time":"20:51:06"},{"tripId":"14962297","time":"11:49:00"},{"tripId":"14962296","time":"12:49:00"},{"tripId":"14962299","time":"09:48:45"},{"tripId":"14962298","time":"10:48:52"},{"tripId":"15261059","time":"12:49:00"},{"tripId":"14962305","time":"15:49:14"},{"tripId":"14962304","time":"16:49:06"},{"tripId":"15261083","time":"17:48:00"},{"tripId":"15261085","time":"16:48:14"},{"tripId":"15261084","time":"19:42:45"},{"tripId":"15261087","time":"12:48:00"},{"tripId":"15261086","time":"18:43:00"},{"tripId":"15261089","time":"14:48:00"},{"tripId":"15261088","time":"15:48:00"},{"tripId":"15260768","time":"08:43:09"},{"tripId":"15261033","time":"13:50:00"},{"tripId":"15261034","time":"12:50:00"},{"tripId":"15261035","time":"18:48:06"},{"tripId":"15261036","time":"17:48:14"},{"tripId":"15261038","time":"11:50:00"},{"tripId":"15261039","time":"15:51:06"},{"tripId":"14962279","time":"14:50:14"},{"tripId":"14962278","time":"09:48:14"},{"tripId":"14962277","time":"10:52:14"},{"tripId":"14962276","time":"15:51:00"},{"tripId":"14962275","time":"11:50:14"},{"tripId":"14962274","time":"16:49:06"},{"tripId":"14962273","time":"17:48:00"},{"tripId":"14962272","time":"18:47:52"},{"tripId":"14962271","time":"12:50:14"},{"tripId":"14962282","time":"19:47:52"},{"tripId":"14962280","time":"21:52:52"},{"tripId":"14962281","time":"20:47:52"},{"tripId":"15261069","time":"14:49:14"},{"tripId":"15261068","time":"15:49:14"},{"tripId":"15261067","time":"16:49:00"},{"tripId":"15261066","time":"17:48:52"},{"tripId":"15261065","time":"18:50:52"},{"tripId":"15261064","time":"19:50:52"},{"tripId":"15261063","time":"20:50:45"},{"tripId":"15261062","time":"09:48:45"},{"tripId":"15261061","time":"10:48:52"},{"tripId":"15261060","time":"11:49:00"},{"tripId":"14962011","time":"19:38:00"},{"tripId":"14962010","time":"19:10:00"}]