[{"tripId":"15261078","time":"17:39:27"},{"tripId":"15261079","time":"16:39:27"},{"tripId":"15261072","time":"12:39:27"},{"tripId":"15261073","time":"10:39:27"},{"tripId":"15261096","time":"10:39:06"},{"tripId":"15261097","time":"09:39:06"},{"tripId":"15261094","time":"12:39:06"},{"tripId":"15261095","time":"11:39:06"},{"tripId":"15260775","time":"05:23:21"},{"tripId":"15260776","time":"05:57:21"},{"tripId":"15261098","time":"15:39:06"},{"tripId":"15261099","time":"19:34:06"},{"tripId":"15261074","time":"20:41:27"},{"tripId":"15261075","time":"19:41:27"},{"tripId":"15261076","time":"09:39:27"},{"tripId":"15261077","time":"18:41:27"},{"tripId":"15261071","time":"13:39:27"},{"tripId":"15261100","time":"18:34:06"},{"tripId":"15261101","time":"17:39:06"},{"tripId":"15261102","time":"16:39:06"},{"tripId":"15261103","time":"14:39:06"},{"tripId":"15261104","time":"13:39:06"},{"tripId":"15260777","time":"06:47:21"},{"tripId":"15260778","time":"07:17:21"},{"tripId":"14962341","time":"13:39:06"},{"tripId":"14962340","time":"14:39:06"},{"tripId":"15261080","time":"15:39:27"},{"tripId":"14962332","time":"11:39:06"},{"tripId":"14962333","time":"10:39:06"},{"tripId":"14962336","time":"19:34:06"},{"tripId":"14962337","time":"18:34:06"},{"tripId":"14962334","time":"09:39:06"},{"tripId":"14962335","time":"15:39:06"},{"tripId":"14962338","time":"17:39:06"},{"tripId":"14962339","time":"16:39:06"},{"tripId":"15260779","time":"07:47:21"},{"tripId":"15261047","time":"20:39:06"},{"tripId":"15261046","time":"21:44:06"},{"tripId":"14962308","time":"13:39:27"},{"tripId":"15261049","time":"18:39:06"},{"tripId":"15261048","time":"19:39:06"},{"tripId":"14962331","time":"12:39:06"},{"tripId":"14962291","time":"13:39:50"},{"tripId":"14962290","time":"14:39:50"},{"tripId":"14962293","time":"11:39:50"},{"tripId":"14962292","time":"12:39:50"},{"tripId":"14962295","time":"09:39:06"},{"tripId":"14962294","time":"10:41:50"},{"tripId":"15260781","time":"08:34:21"},{"tripId":"15260783","time":"16:58:21"},{"tripId":"15260782","time":"16:30:21"},{"tripId":"15260785","time":"18:12:41"},{"tripId":"15260784","time":"17:33:41"},{"tripId":"15261052","time":"15:40:50"},{"tripId":"15261053","time":"14:39:50"},{"tripId":"15261050","time":"17:39:06"},{"tripId":"15261051","time":"16:40:06"},{"tripId":"15261056","time":"11:39:50"},{"tripId":"15261057","time":"10:41:50"},{"tripId":"15261054","time":"13:39:50"},{"tripId":"15261055","time":"12:39:50"},{"tripId":"15261058","time":"09:39:06"},{"tripId":"14962022","time":"18:12:41"},{"tripId":"14962023","time":"19:00:41"},{"tripId":"14962020","time":"16:58:21"},{"tripId":"14962021","time":"17:33:41"},{"tripId":"14962024","time":"19:28:41"},{"tripId":"14962309","time":"12:39:27"},{"tripId":"14962318","time":"14:39:27"},{"tripId":"14962319","time":"11:39:27"},{"tripId":"14962314","time":"18:41:27"},{"tripId":"14962315","time":"17:39:27"},{"tripId":"14962316","time":"16:39:27"},{"tripId":"14962317","time":"15:39:27"},{"tripId":"14962310","time":"10:39:27"},{"tripId":"14962311","time":"20:41:27"},{"tripId":"14962312","time":"19:41:27"},{"tripId":"14962313","time":"09:39:27"},{"tripId":"15261081","time":"14:39:27"},{"tripId":"15261082","time":"11:39:27"},{"tripId":"15260786","time":"18:58:41"},{"tripId":"15260780","time":"08:06:21"},{"tripId":"15260787","time":"19:26:41"},{"tripId":"14962288","time":"16:40:06"},{"tripId":"14962289","time":"15:40:50"},{"tripId":"14962286","time":"18:39:06"},{"tripId":"14962287","time":"17:39:06"},{"tripId":"14962284","time":"20:39:06"},{"tripId":"14962285","time":"19:39:06"},{"tripId":"14962283","time":"21:44:06"},{"tripId":"14962017","time":"08:07:00"},{"tripId":"14962016","time":"07:48:00"},{"tripId":"14962015","time":"07:18:00"},{"tripId":"14962014","time":"06:48:00"},{"tripId":"14962013","time":"05:58:00"},{"tripId":"14962012","time":"05:24:00"},{"tripId":"14962019","time":"16:30:21"},{"tripId":"14962018","time":"08:37:00"}]