[{"tripId":"15263420","time":"07:23:00"},{"tripId":"15263438","time":"13:30:00"},{"tripId":"15263439","time":"15:28:00"},{"tripId":"15263432","time":"09:21:00"},{"tripId":"15263433","time":"11:21:00"},{"tripId":"15263430","time":"17:26:00"},{"tripId":"15263431","time":"19:28:00"},{"tripId":"15263435","time":"15:28:00"},{"tripId":"14964631","time":"19:31:00"},{"tripId":"14964630","time":"19:31:00"},{"tripId":"14964633","time":"13:32:00"},{"tripId":"14964632","time":"17:36:00"},{"tripId":"14964635","time":"16:01:00"},{"tripId":"14964637","time":"09:22:00"},{"tripId":"14964636","time":"11:21:00"},{"tripId":"14964639","time":"17:26:00"},{"tripId":"14964638","time":"07:23:00"},{"tripId":"14964640","time":"19:28:00"},{"tripId":"14964628","time":"09:22:00"},{"tripId":"14964629","time":"07:23:00"},{"tripId":"14964627","time":"11:21:00"},{"tripId":"14964624","time":"17:36:00"},{"tripId":"15263440","time":"17:26:00"},{"tripId":"15263415","time":"17:36:00"},{"tripId":"15263416","time":"16:01:00"},{"tripId":"15263417","time":"13:29:00"},{"tripId":"15263418","time":"11:21:00"},{"tripId":"15263419","time":"09:22:00"},{"tripId":"15263436","time":"11:21:00"},{"tripId":"15263434","time":"13:30:00"},{"tripId":"15263421","time":"19:31:00"},{"tripId":"14964626","time":"13:32:00"},{"tripId":"14964625","time":"16:01:00"},{"tripId":"14964641","time":"09:21:00"},{"tripId":"14964650","time":"19:28:00"},{"tripId":"15263429","time":"07:23:00"},{"tripId":"15263428","time":"09:22:00"},{"tripId":"15263426","time":"16:01:00"},{"tripId":"15263437","time":"09:21:00"},{"tripId":"14964644","time":"15:28:00"},{"tripId":"14964645","time":"11:21:00"},{"tripId":"14964646","time":"09:21:00"},{"tripId":"14964647","time":"13:30:00"},{"tripId":"14964642","time":"11:21:00"},{"tripId":"14964643","time":"13:30:00"},{"tripId":"14964648","time":"15:28:00"},{"tripId":"14964649","time":"17:26:00"},{"tripId":"15263441","time":"19:28:00"},{"tripId":"15263424","time":"13:29:00"},{"tripId":"15263427","time":"11:21:00"},{"tripId":"15263423","time":"17:36:00"},{"tripId":"15263422","time":"19:31:00"}]