[{"tripId":"15263313","time":"11:18:51"},{"tripId":"15263312","time":"10:23:51"},{"tripId":"15263311","time":"16:22:28"},{"tripId":"15263310","time":"08:18:51"},{"tripId":"15263293","time":"19:36:02"},{"tripId":"15263294","time":"18:44:47"},{"tripId":"15263296","time":"17:04:47"},{"tripId":"15263297","time":"15:52:28"},{"tripId":"15263295","time":"18:04:47"},{"tripId":"15263291","time":"21:33:51"},{"tripId":"15263298","time":"14:52:28"},{"tripId":"15263299","time":"13:50:39"},{"tripId":"15263368","time":"17:20:39"},{"tripId":"15263367","time":"19:20:39"},{"tripId":"14964503","time":"20:30:01"},{"tripId":"14964502","time":"21:32:01"},{"tripId":"14964501","time":"17:33:47"},{"tripId":"14964506","time":"18:04:47"},{"tripId":"14964505","time":"18:43:47"},{"tripId":"14964504","time":"19:36:02"},{"tripId":"14964509","time":"14:52:28"},{"tripId":"14964508","time":"15:52:28"},{"tripId":"14963301","time":"07:52:43"},{"tripId":"14964576","time":"19:19:44"},{"tripId":"14964577","time":"17:19:44"},{"tripId":"14964578","time":"15:19:44"},{"tripId":"14964579","time":"13:19:44"},{"tripId":"15263308","time":"17:35:47"},{"tripId":"15263309","time":"17:04:47"},{"tripId":"15263300","time":"12:50:39"},{"tripId":"15263301","time":"11:50:39"},{"tripId":"15263302","time":"10:48:51"},{"tripId":"15263304","time":"08:48:51"},{"tripId":"15263305","time":"07:50:02"},{"tripId":"15263306","time":"06:50:02"},{"tripId":"15263307","time":"05:50:02"},{"tripId":"15263354","time":"16:25:39"},{"tripId":"15263353","time":"14:25:39"},{"tripId":"15263351","time":"10:23:51"},{"tripId":"14964510","time":"13:50:39"},{"tripId":"14964511","time":"12:50:39"},{"tripId":"14964512","time":"11:50:39"},{"tripId":"14964513","time":"10:48:51"},{"tripId":"14964514","time":"09:48:51"},{"tripId":"14964515","time":"08:50:39"},{"tripId":"14964516","time":"07:50:02"},{"tripId":"14964517","time":"06:50:02"},{"tripId":"14964518","time":"05:50:02"},{"tripId":"14964519","time":"17:36:47"},{"tripId":"15263290","time":"17:32:47"},{"tripId":"15263292","time":"20:31:51"},{"tripId":"15263345","time":"19:18:51"},{"tripId":"15263346","time":"17:25:39"},{"tripId":"15263347","time":"15:25:39"},{"tripId":"15263369","time":"15:20:39"},{"tripId":"14964507","time":"17:03:47"},{"tripId":"14964558","time":"11:23:51"},{"tripId":"14964559","time":"09:23:51"},{"tripId":"14964554","time":"19:18:51"},{"tripId":"14964555","time":"17:25:39"},{"tripId":"14964556","time":"15:25:39"},{"tripId":"14964557","time":"13:24:44"},{"tripId":"14964499","time":"07:24:02"},{"tripId":"14964498","time":"18:06:47"},{"tripId":"14964583","time":"12:19:44"},{"tripId":"14964582","time":"10:19:44"},{"tripId":"14964581","time":"09:19:44"},{"tripId":"14964580","time":"11:19:44"},{"tripId":"14964586","time":"18:19:44"},{"tripId":"14964585","time":"16:19:44"},{"tripId":"14964584","time":"14:19:44"},{"tripId":"15263355","time":"18:23:51"},{"tripId":"15263352","time":"12:22:44"},{"tripId":"15263350","time":"09:23:51"},{"tripId":"15262087","time":"07:53:43"},{"tripId":"14964564","time":"18:23:51"},{"tripId":"15263348","time":"13:24:44"},{"tripId":"15263349","time":"11:24:44"},{"tripId":"14964521","time":"08:20:39"},{"tripId":"14964520","time":"17:06:47"},{"tripId":"14964523","time":"10:23:51"},{"tripId":"14964522","time":"16:22:28"},{"tripId":"14964524","time":"11:18:51"},{"tripId":"15263289","time":"16:22:28"},{"tripId":"15263288","time":"07:24:02"},{"tripId":"15263287","time":"18:04:47"},{"tripId":"15263375","time":"14:20:39"},{"tripId":"15263374","time":"12:19:44"},{"tripId":"15263377","time":"18:20:39"},{"tripId":"15263376","time":"16:20:39"},{"tripId":"15263371","time":"11:18:51"},{"tripId":"15263370","time":"13:19:44"},{"tripId":"15263373","time":"10:18:51"},{"tripId":"15263372","time":"09:18:51"},{"tripId":"14964561","time":"12:22:44"},{"tripId":"14964560","time":"10:23:51"},{"tripId":"14964563","time":"16:25:39"},{"tripId":"14964562","time":"14:24:44"},{"tripId":"15263303","time":"09:48:51"}]